Workbook

Sheet All Features
A1: Category | B1: Feature | C1: Description | D1: State | E1: Priority | F1: Notes | G1: Owner | H1: Target Date
A2: Auth & Users | B2: User Registration | C2: Sign up with email/password | D2: Production | E2: P0 | F2: Devise-based
A3: Auth & Users | B3: User Login | C3: Email/password authentication | D3: Production | E3: P0 | F3: Working in Phase 1
A4: Auth & Users | B4: User Roles | C4: Admin vs regular user permissions | D4: Production | E4: P0 | F4: Basic role system
A5: Auth & Users | B5: User Profile | C5: View/edit personal information | D5: Production | E5: P1 | F5: Basic profile working
A6: Auth & Users | B6: Password Reset | C6: Email-based password recovery | D6: Test | E6: P1 | F6: Devise provides this
A7: Auth & Users | B7: Multi-factor Auth | C7: 2FA for enhanced security | D7: Idea | E7: P3 | F7: Future consideration
A8: Event Management | B8: Create Event | C8: Admin can create new events | D8: Production | E8: P0 | F8: Working
A9: Event Management | B9: Edit Event | C9: Modify event details | D9: Test | E9: P0 | F9: Needs UAT
A10: Event Management | B10: Delete Event | C10: Remove events | D10: Test | E10: P1 | F10: Needs UAT
A11: Event Management | B11: Event Details | C11: Name, description, date/time | D11: Production | E11: P0 | F11: Complete
A12: Event Management | B12: Event Capacity | C12: Max attendees tracking | D12: Production | E12: P1 | F12: Implemented
A13: Event Management | B13: RSVP Deadline | C13: Cut-off date for responses | D13: Production | E13: P1 | F13: Implemented
... A93: Testing & Quality | B93: Accessibility | C93: WCAG compliance | D93: Idea | E93: P3 | F93: Future consideration

Sheet By Priority
A1: Category | B1: Feature | C1: Description | D1: State | E1: Priority | F1: Notes | G1: Owner | H1: Target Date
A2: Infrastructure | B2: Database (PostgreSQL) | C2: Production database | D2: Design | E2: P0 | F2: Configured but not deployed
A3: RSVP & Attendance | B3: Quick RSVP (Public) | C3: No-login RSVP via shareable link | D3: Idea | E3: P0 | F3: BLOCKER for Boat Party - needs email workaround
A4: Auth & Users | B4: User Registration | C4: Sign up with email/password | D4: Production | E4: P0 | F4: Devise-based
A5: Auth & Users | B5: User Login | C5: Email/password authentication | D5: Production | E5: P0 | F5: Working in Phase 1
A6: Auth & Users | B6: User Roles | C6: Admin vs regular user permissions | D6: Production | E6: P0 | F6: Basic role system
A7: Event Management | B7: Create Event | C7: Admin can create new events | D7: Production | E7: P0 | F7: Working
A8: Event Management | B8: Event Details | C8: Name, description, date/time | D8: Production | E8: P0 | F8: Complete
A9: RSVP & Attendance | B9: RSVP Status | C9: Yes/Maybe/No responses | D9: Production | E9: P0 | F9: Fixed in Phase 1
A10: RSVP & Attendance | B10: RSVP Data Model | C10: EventParticipant tracking | D10: Production | E10: P0 | F10: Correct architecture
A11: RSVP & Attendance | B11: View RSVPs | C11: Admin can see all responses | D11: Production | E11: P0 | F11: Working in admin panel
A12: Admin Features | B12: Admin Dashboard | C12: Overview of all events | D12: Production | E12: P0 | F12: Working with nil checks
A13: Admin Features | B13: Admin Panel | C13: Administrative interface | D13: Production | E13: P0 | F13: Rails Admin or custom
... A93: Testing & Quality | B93: Accessibility | C93: WCAG compliance | D93: Idea | E93: P3 | F93: Future consideration

Sheet By State
A1: Category | B1: Feature | C1: Description | D1: State | E1: Priority | F1: Notes | G1: Owner | H1: Target Date
A2: Auth & Users | B2: User Registration | C2: Sign up with email/password | D2: Production | E2: P0 | F2: Devise-based
A3: Auth & Users | B3: User Login | C3: Email/password authentication | D3: Production | E3: P0 | F3: Working in Phase 1
A4: Auth & Users | B4: User Roles | C4: Admin vs regular user permissions | D4: Production | E4: P0 | F4: Basic role system
A5: Event Management | B5: Create Event | C5: Admin can create new events | D5: Production | E5: P0 | F5: Working
A6: Event Management | B6: Event Details | C6: Name, description, date/time | D6: Production | E6: P0 | F6: Complete
A7: RSVP & Attendance | B7: RSVP Status | C7: Yes/Maybe/No responses | D7: Production | E7: P0 | F7: Fixed in Phase 1
A8: RSVP & Attendance | B8: RSVP Data Model | C8: EventParticipant tracking | D8: Production | E8: P0 | F8: Correct architecture
A9: RSVP & Attendance | B9: View RSVPs | C9: Admin can see all responses | D9: Production | E9: P0 | F9: Working in admin panel
A10: Admin Features | B10: Admin Dashboard | C10: Overview of all events | D10: Production | E10: P0 | F10: Working with nil checks
A11: Admin Features | B11: Admin Panel | C11: Administrative interface | D11: Production | E11: P0 | F11: Rails Admin or custom
A12: Admin Features | B12: Event Management | C12: Admin CRUD for events | D12: Production | E12: P0 | F12: Working
A13: Infrastructure | B13: Database (SQLite) | C13: Development database | D13: Production | E13: P0 | F13: Working
... A93: Testing & Quality | B93: Accessibility | C93: WCAG compliance | D93: Idea | E93: P3 | F93: Future consideration

Sheet Summary Dashboard
A1: CONFAB/EVM1 FEATURE INVENTORY SUMMARY
A3: Generated: | B3: February 14, 2026
A4: Total Features: | B4: =COUNTA('All Features'!B2:B1000) -> 92
A6: FEATURES BY STATE
A7: State | B7: Count | C7: Percentage
A8: Production | B8: =COUNTIF('All Features'!D:D,"Production") -> 22 | C8: =B8/$B$4 -> 0.23913043
A9: Test | B9: =COUNTIF('All Features'!D:D,"Test") -> 12 | C9: =B9/$B$4 -> 0.13043478
A10: Dev | B10: =COUNTIF('All Features'!D:D,"Dev") -> 2 | C10: =B10/$B$4 -> 0.02173913
A11: Design | B11: =COUNTIF('All Features'!D:D,"Design") -> 4 | C11: =B11/$B$4 -> 0.043478261
A12: UAT | B12: =COUNTIF('All Features'!D:D,"UAT") -> 0 | C12: =B12/$B$4 -> 0
A13: Idea | B13: =COUNTIF('All Features'!D:D,"Idea") -> 52 | C13: =B13/$B$4 -> 0.56521739
A15: FEATURES BY PRIORITY
A16: Priority | B16: Count | C16: Percentage
A17: P0 | B17: =COUNTIF('All Features'!E:E,"P0") -> 16 | C17: =B17/$B$4 -> 0.17391304
A18: P1 | B18: =COUNTIF('All Features'!E:E,"P1") -> 23 | C18: =B18/$B$4 -> 0.25
A19: P2 | B19: =COUNTIF('All Features'!E:E,"P2") -> 34 | C19: =B19/$B$4 -> 0.36956522
A20: P3 | B20: =COUNTIF('All Features'!E:E,"P3") -> 19 | C20: =B20/$B$4 -> 0.20652174
A23: TOP CATEGORIES
A24: Category | B24: Count
A25: Event Management | B25: =COUNTIF('All Features'!A:A,"Event Management") -> 10
A26: RSVP & Attendance | B26: =COUNTIF('All Features'!A:A,"RSVP & Attendance") -> 9
A27: Communication | B27: =COUNTIF('All Features'!A:A,"Communication") -> 7
A28: Admin Features | B28: =COUNTIF('All Features'!A:A,"Admin Features") -> 7
A29: Infrastructure | B29: =COUNTIF('All Features'!A:A,"Infrastructure") -> 8
A30: Contact Enhancement | B30: =COUNTIF('All Features'!A:A,"Contact Enhancement") -> 6
A31: Resource Matching | B31: =COUNTIF('All Features'!A:A,"Resource Matching") -> 5

Sheet Next Actions
A1: IMMEDIATE NEXT ACTIONS
A3: Priority | B3: Action Item | C3: Category
A4: P0 | B4: Design & implement Quick RSVP (public RSVP link, no email required) | C4: RSVP & Attendance
A5: P0 | B5: Test RSVP UI - verify buttons actually change status | C5: RSVP & Attendance
A6: P0 | B6: Fix Sidekiq connection_pool issue | C6: Infrastructure
A7: P0 | B7: Rename project ev1 → evm1 and move to C:\evm1 | C7: Infrastructure
A8: P1 | B8: Test bulk invite functionality | C8: Participant Mgmt
A9: P1 | B9: Test check-in system | C9: RSVP & Attendance
A10: P1 | B10: Verify email notifications work after Sidekiq fix | C10: Communication
A11: P1 | B11: Complete UAT on all "Test" state features | C11: Testing & Quality
A12: P1 | B12: Set up FactoryBot for volume testing | C12: Testing & Quality
A13: P2 | B13: Design contact/identity enhancement (multiple emails, phones) | C13: Contact Enhancement
A14: P2 | B14: Decide on event type specialization (Conference vs Convention) | C14: Event Types
... A17: P3 | B17: Document resource matching concept for future discussion | C17: Resource Matching
A20: KEY BLOCKERS FOR BOAT ANNIVERSARY PARTY
A21: 1. Quick RSVP feature (no email required) - people are on Facebook, not in email list
A22: 2. Email notification working (fix Sidekiq connection_pool)
A23: 3. Testing RSVP button functionality
